piperf3/__init__.py
piperf3/_version.py
piperf3/cli.py
piperf3/constants.py
piperf3/display.py
piperf3/models.py
piperf3/plotting.py
piperf3/runner.py
piperf3-0.0.11.dist-info/METADATA
piperf3-0.0.11.dist-info/WHEEL
piperf3-0.0.11.dist-info/entry_points.txt
piperf3-0.0.11.dist-info/licenses/LICENSE
piperf3-0.0.11.dist-info/RECORD
