Metadata-Version: 2.4
Name: piperf3
Version: 0.0.11
Summary: A Python wrapper for iperf3 with configuration management, plotting, and CLI interface
Author-email: Sam Welborn <swelborn@lbl.gov>
License-File: LICENSE
Requires-Python: >=3.12
Requires-Dist: matplotlib>=3.10.6
Requires-Dist: numpy>=2.3.2
Requires-Dist: pandas>=2.3.2
Requires-Dist: pydantic-settings>=2.10.1
Requires-Dist: pydantic>=2.11.7
Requires-Dist: python-dotenv>=1.1.1
Requires-Dist: pyyaml>=6.0.2
Requires-Dist: rich>=14.1.0
Requires-Dist: seaborn>=0.12.0
Requires-Dist: typer>=0.17.3
